AUTHORS
ChangeLog
LICENSE
README.md
requirements.txt
setup.cfg
setup.py
tox.ini
./celery_actions/__init__.py
./celery_actions/async.py
./celery_actions/base.py
celery_actions/__init__.py
celery_actions/async.py
celery_actions/base.py
mistral_celery_actions.egg-info/PKG-INFO
mistral_celery_actions.egg-info/SOURCES.txt
mistral_celery_actions.egg-info/dependency_links.txt
mistral_celery_actions.egg-info/entry_points.txt
mistral_celery_actions.egg-info/not-zip-safe
mistral_celery_actions.egg-info/pbr.json
mistral_celery_actions.egg-info/requires.txt
mistral_celery_actions.egg-info/top_level.txt