Metadata-Version: 1.1
Name: mistral-celery-actions
Version: 1.0.1
Summary: A Mistral action to call celery tasks
Home-page: https://github.com/collabo-br/mistral-celery-actions
Author: Collabo Team
Author-email: ariane.rocha@collabo.com.br
License: MIT License
Download-URL: https://github.com/collabo-br/mistral-celery-actions/archive/1.0.0.tar.gz
Keywords: workflow,actions,mistral,celery
Platform: UNKNOWN
Classifier: Intended Audience :: Developers
Classifier: Natural Language :: English
Classifier: License :: OSI Approved :: Apache Software License
Classifier: Programming Language :: Python
Classifier: Programming Language :: Python :: 2.7
Classifier: Topic :: Internet
Classifier: Topic :: Utilities
